{
 "secNum": "3.5",
 "chip": "Google TPU v1",
 "title": "TPU v1 · 后道 BEOL(Back-End-of-Line):在做好的晶体管之上叠十余层铜金属 + 层间介质 + 通孔 via,把 256×256 阵列、24MiB UB 与控制逻辑「连」成 ⑧ 设计的整颗电路",
 "oneLine": "本案例落到「后道 BEOL:做互连」小节:前道 FEOL 在衬底里造好了晶体管(MAC、SRAM、控制逻辑的「器件本体」),但此刻它们还是一堆互不相连的孤岛;BEOL 就是在晶体管之上「叠楼+布线」——一层层铺铜金属(M1..Mx)、用层间介质(low-k ILD)把每层横向隔开、用通孔(via)在层间上下打通,最后做出钝化层与对外焊盘。⑧ 后端布局布线时在版图里规划的每一根连线,正是在这一步变成晶圆上真实的铜导线;现代大芯片常有十余层金属,TPU v1 那块 28nm、≤331mm² die 上的 256×256 脉动阵列、24MiB Unified Buffer、累加器与控制逻辑,就靠这套铜互连被连成完整电路、再留出 I/O 焊盘交给 ⑫ 封装。",
 "svg": "<svg class=\"cs-svg\" viewBox=\"0 0 720 410\" xmlns=\"http://www.w3.org/2000/svg\"><defs><marker id=\"csar\" markerWidth=\"9\" markerHeight=\"9\" refX=\"6.5\" refY=\"3\" orient=\"auto\"><path d=\"M0,0 L7,3 L0,6 Z\" fill=\"#94a3b8\"/></marker></defs><text class=\"cs-note\" x=\"40\" y=\"26\">后道 BEOL = 在晶体管之上「叠楼+布线」:多层铜金属(M1..Mx)+ 层间介质 + 通孔 via,把 ⑧ 后端布的线变成真实金属,连成整颗 TPU</text><g class=\"cs-part\" data-k=\"feol\" data-g=\"feol\"><rect class=\"cs-box\" x=\"34\" y=\"320\" width=\"652\" height=\"56\" rx=\"8\" fill=\"#fee2e2\" stroke=\"#fca5a5\"/><text class=\"cs-t\" x=\"360\" y=\"344\">前道 FEOL:衬底 + 晶体管层(256×256 MAC、SRAM、控制逻辑的「器件」本体)</text><text class=\"cs-sub\" x=\"360\" y=\"364\">BEOL 之前已造好的「一楼地基」——晶体管做好了,但还没连起来</text></g><polyline class=\"cs-arr\" points=\"360,320 360,306\" fill=\"none\" marker-end=\"url(#csar)\"/><text class=\"cs-note\" x=\"468\" y=\"306\">↑ BEOL 接力点:在它之上布线</text><g class=\"cs-part\" data-k=\"m1\" data-g=\"m1\"><rect class=\"cs-box\" x=\"34\" y=\"278\" width=\"652\" height=\"26\" rx=\"4\" fill=\"#dbeafe\" stroke=\"#93c5fd\"/><text class=\"cs-cellt\" x=\"360\" y=\"296\">M1 局部互连(最细最密;直接搭到晶体管的源漏栅触点)</text></g><g class=\"cs-part\" data-k=\"via\" data-g=\"via\"><rect class=\"cs-cell\" x=\"150\" y=\"266\" width=\"12\" height=\"12\"/><rect class=\"cs-cell\" x=\"358\" y=\"266\" width=\"12\" height=\"12\"/><rect class=\"cs-cell\" x=\"560\" y=\"266\" width=\"12\" height=\"12\"/></g><g class=\"cs-part\" data-k=\"mid\" data-g=\"mid\"><rect class=\"cs-box\" x=\"34\" y=\"232\" width=\"652\" height=\"26\" rx=\"4\" fill=\"#bfdbfe\" stroke=\"#60a5fa\"/><text class=\"cs-cellt\" x=\"360\" y=\"250\">M2..M5 中间层(渐粗;在阵列/SRAM/控制块之间走信号与短电源)</text></g><g class=\"cs-part\" data-k=\"via2\" data-g=\"via\"><rect class=\"cs-cell\" x=\"240\" y=\"220\" width=\"12\" height=\"12\"/><rect class=\"cs-cell\" x=\"460\" y=\"220\" width=\"12\" height=\"12\"/></g><g class=\"cs-part\" data-k=\"top\" data-g=\"top\"><rect class=\"cs-box\" x=\"34\" y=\"186\" width=\"652\" height=\"26\" rx=\"4\" fill=\"#93c5fd\" stroke=\"#3b82f6\"/><text class=\"cs-cellt\" x=\"360\" y=\"204\">顶层金属(最粗;全片时钟分发、电源/地网格、长距离总线)</text></g><g class=\"cs-part\" data-k=\"ild\" data-g=\"ild\"><rect class=\"cs-box\" x=\"34\" y=\"150\" width=\"652\" height=\"26\" rx=\"4\" fill=\"#f1f5f9\" stroke=\"#cbd5e1\"/><text class=\"cs-cellt\" x=\"360\" y=\"168\">层间介质 ILD(low-k 绝缘层:把每层金属彼此隔开,只在 via 处导通)</text></g><g class=\"cs-part\" data-k=\"pad\" data-g=\"pad\"><rect class=\"cs-box\" x=\"34\" y=\"104\" width=\"652\" height=\"34\" rx=\"6\" fill=\"#fef9c3\" stroke=\"#fde047\"/><text class=\"cs-t\" x=\"360\" y=\"126\">钝化 + I/O 焊盘(pad):BEOL 最上面,留出对外接口 → 交 ⑫ 封装</text></g><polyline class=\"cs-arr\" points=\"360,150 360,138\" fill=\"none\" marker-end=\"url(#csar)\"/><text class=\"cs-note\" x=\"40\" y=\"64\">剖面自下而上:FEOL 晶体管 → M1(细)→ 中间层 → 顶层(粗)→ 焊盘;层与层之间用 via 上下导通,用 ILD 横向隔离</text><text class=\"cs-note\" x=\"40\" y=\"84\">现代大芯片常有十余层金属;TPU v1(28nm、≤331mm²)的 256×256 阵列、24MiB UB、控制逻辑就靠这套铜互连连成 ⑧ 设计的整颗电路</text><text class=\"cs-note\" x=\"40\" y=\"396\">诚实边界:铜大马士革、low-k ILD、十余层金属、CMP 平坦化均为这类 28nm 大芯片的通行 BEOL 实践;TPU v1 不公开其私有金属层数/介质配方/代工厂,本图借已知结构作被布线对象讲概念。</text></svg>",
 "legend": [
  {
   "k": "feol",
   "name": "前道 FEOL(器件层/地基)",
   "desc": "BEOL 的「接力点」。前道工序(在前几小节)已在硅衬底里造好了晶体管本体——TPU 那 65,536 个 8-bit MAC、SRAM(Unified Buffer/累加器)、控制逻辑的「器件」都已成形,但它们此刻还是一堆互不相连的孤岛。BEOL 不再碰晶体管,而是在这层「一楼地基」之上叠金属、布线,把孤岛连成电路。前道决定「有哪些器件」,后道决定「它们怎么连」。"
  },
  {
   "k": "m1",
   "name": "M1 局部互连(最细最密)",
   "desc": "最靠近晶体管的第一层金属,也是最细、最密的一层。它直接搭到晶体管的源/漏/栅触点上,负责「最后一公里」的局部连接——把相邻几个器件先连成单元。对 TPU 这种由海量规整 MAC 单元拼成的脉动阵列,M1 的密度与一致性直接决定每个 MAC 内部能否被正确连起来;一旦这层断线或短路,落在阵列里就是一颗 die 报废。"
  },
  {
   "k": "mid",
   "name": "中间金属层(M2..Mx,渐粗)",
   "desc": "M1 之上的若干层金属,从细到粗逐层加宽。它们在阵列、SRAM、控制块这些「楼层」之间走信号线和较短的电源线——好比楼里的走廊把各房间连通。⑧ 后端布线把绝大多数连线分摊到这些中间层,层越往上、线越粗、走得越远、电阻越小;布线工具正是靠「分层走线」才把一整颗芯片密密麻麻的连接塞进有限的金属层里。"
  },
  {
   "k": "top",
   "name": "顶层金属(最粗:时钟/电源/长总线)",
   "desc": "最上面、最厚最粗的几层金属,专做「全局大事」:把时钟分发到全片每个角落、铺设电源/地(power/ground)网格供电、走芯片级的长距离总线。线粗 = 电阻低、能扛大电流、压低供电压降与时钟偏斜。对 TPU 这种全片同步推动 256×256 阵列的大芯片,顶层金属的电源网格和时钟树是否够「粗」,直接关系到 700MHz 全阵列能否稳定供电与同步。"
  },
  {
   "k": "via",
   "name": "通孔 via(层间上下导通)",
   "desc": "金属层默认彼此被绝缘层隔开,只有在 via(通孔)的位置才上下打通、让电流从一层流到相邻层——好比楼与楼之间的电梯/竖井。一根从晶体管出发、要走到顶层电源网的连接,往往要穿过好几层金属、靠一串 via 接力上去。via 是 BEOL 里最容易出可靠性问题的地方(电迁移、空洞),所以关键连接常并联多个 via 来留冗余。"
  }
 ],
 "steps": [
  {
   "keys": [
    "feol"
   ],
   "cap": "① 接棒 FEOL:前道已造好晶体管(MAC/SRAM/控制逻辑),但它们还是互不相连的孤岛;BEOL 在这层「地基」之上开始叠金属、布线,不再改动器件本身。"
  },
  {
   "keys": [
    "m1",
    "via"
   ],
   "cap": "② 铺 M1 + 打 via:做最细最密的第一层铜金属直接搭到晶体管触点,把相邻器件先连成单元;用 via 在层间预留上下导通点。"
  },
  {
   "keys": [
    "mid",
    "ild"
   ],
   "cap": "③ 叠中间层 + 隔介质:逐层铺渐粗的中间金属在阵列/SRAM/控制块之间走信号,层与层之间填 low-k 层间介质(ILD)横向绝缘,只在 via 处导通。"
  },
  {
   "keys": [
    "top"
   ],
   "cap": "④ 顶层金属做全局:最粗的顶层走时钟分发、电源/地网格与长总线——保证 700MHz 推动整片 256×256 阵列时供得上电、同步得了。"
  },
  {
   "keys": [
    "pad"
   ],
   "cap": "⑤ 钝化 + 焊盘收尾:在最上面做钝化保护层并露出 I/O 焊盘(pad),把连好的整颗电路留出对外接口,交给 ⑫ 封装。"
  }
 ],
 "before": [
  "<b>前道(FEOL)已完工并验过</b>:进 BEOL 前,衬底里的晶体管——TPU 的 65,536 个 MAC、SRAM、控制逻辑——必须都已造好且电学参数达标;后道只「连线」不「造器件」,前道器件层有问题,后面布再多金属也救不回来。",
  "<b>带回 ⑧ 后端布线的金属规划</b>:每层金属走什么、哪些是信号层、哪些是电源/时钟层、via 落在哪里,都由 ⑧ 布局布线(P&R)的版图定死;BEOL 是把那套「图上的线」逐层兑现成真实铜线,开工前要对齐用的是哪一版布线结果。",
  "<b>定金属/介质工艺栈</b>:选好导体(铜大马士革工艺)、层间介质(low-k 绝缘材料)、每层的厚度与最小线宽/间距,以及总共叠几层金属;这套「金属层栈」必须和 ⑧ 布线时假设的工艺规则完全一致,否则线连不出来。",
  "<b>对准基准延续</b>:每一层金属都要和下层精确对齐(套刻),via 必须恰好落在上下两层金属的交点上;开工前确认对准标记与套刻预算贯穿整个金属层栈,层间错位会让 via 接不上、整条连线断路。",
  "<b>平坦化预案</b>:每叠一层金属+介质,表面就会起伏;BEOL 要靠化学机械抛光(CMP)把每层磨平再叠下一层,否则上层光刻聚不了焦。开工前要为每层定好 CMP 预案,这是十余层能稳定叠上去的前提。"
 ],
 "during": [
  "<b>自下而上「叠楼+布线」</b>:从最靠晶体管的 M1 开始,逐层铺金属、填层间介质、打 via,一直叠到最粗的顶层——M1 最细最密做局部连接,中间层走信号,顶层做时钟/电源/长总线。每一层都要走一遍(沟槽光刻→刻蚀→填铜→CMP 磨平)的循环,十余层就是十余轮。",
  "<b>铜大马士革:先挖沟再填铜</b>:现代 BEOL 不是「先铺铜再刻」,而是大马士革工艺——先在介质里刻出线沟和 via 孔,再电镀填铜,最后 CMP 把多余的铜磨掉、只留沟里的线。via 和金属常一起填(双大马士革),这样层间导通点和线一次成形。",
  "<b>ILD 横向绝缘、via 纵向导通</b>:层间介质(low-k ILD)的职责是把每层金属彼此隔开、防止串扰与短路,只有在 via 的位置才上下打通。整套互连就是「横向靠金属走线、纵向靠 via 跳层、其余地方靠 ILD 绝缘」三者拼出来的立体网络——⑧ 设计的每根连线在此成为真实的三维铜路径。",
  "<b>顶层扛全局:供电与时钟</b>:越往上金属越粗,因为顶层要承担全片供电(power/ground 网格)和时钟分发这种「大电流、长距离、低容差」的活。线粗 → 电阻低 → 供电压降(IR drop)和时钟偏斜(skew)小;对 TPU 这种 700MHz 全阵列同步的大芯片,顶层电源/时钟网做得好不好,直接决定整片阵列能不能稳定跑起来。",
  "<b>每层 CMP 平坦化是隐形功臣</b>:每叠完一层金属+介质,表面必然起伏,必须用 CMP 磨平再叠下一层——否则上层光刻无法聚焦、线宽全飘。十余层金属能一层层精确叠上去,靠的就是每一层都先磨平;这是 BEOL 默默支撑多层互连的关键工序。",
  "<b>诚实边界</b>:铜双大马士革、low-k ILD、十余层金属层栈、每层 CMP 平坦化、双 via 冗余,都是这类 28nm 大芯片/PCIe 加速卡的通行 BEOL 实践;TPU v1 不公开其私有金属层数、介质配方、布线层栈或代工厂,本节只借其已知结构(256×256 阵列、24MiB UB、控制逻辑、≤331mm² die、28nm)作为被「布线连接」的对象讲 BEOL 概念,不杜撰 TPU 私有的后道工艺数字。"
 ],
 "result": [
  {
   "label": "本步产物",
   "value": "晶体管之上叠好的十余层铜互连 + 层间介质 + via,整颗电路已「连通」"
  },
  {
   "label": "互连结构",
   "value": "M1(细,局部)→ 中间层(渐粗,信号)→ 顶层(最粗,时钟/电源/总线)"
  },
  {
   "label": "三要素分工",
   "value": "金属横向走线、via 纵向跳层、ILD(low-k)负责绝缘隔离"
  },
  {
   "label": "工艺手段",
   "value": "铜双大马士革(挖沟→填铜→CMP)逐层叠,每层 CMP 平坦化"
  },
  {
   "label": "兑现的设计",
   "value": "⑧ 后端布线规划的每根连线,在此变成晶圆上真实的铜导线"
  },
  {
   "label": "对外接口",
   "value": "顶上做钝化保护层 + 露出 I/O 焊盘(pad),交给 ⑫ 封装"
  }
 ],
 "after": [
  "<b>互连完整性检查</b>:量关键金属层的线宽/间距、via 链电阻、层间套刻,确认没有断线(开路)、桥连(短路)或 via 接触不良;BEOL 出的问题往往不是某个器件坏,而是「连线没连对」,要在这里逐层查出来。",
  "<b>晶圆级电学测试(WAT/CP)</b>:用探针在晶圆上点测,看每颗 die 的连线是否导通、电路是否按 ⑧ 设计工作;BEOL 连好后这是第一次能真正「通电试一试」,据此初步判定哪些 die 是好的。",
  "<b>钝化与焊盘交封装</b>:确认最上面的钝化保护层完好、I/O 焊盘暴露正确,把已连成完整电路、留好对外接口的晶圆交给后续 ⑫ 封装去切割、贴片、引线/凸点,最终做成 TPU 那块 PCIe 加速卡。",
  "<b>反馈调后道工艺</b>:把全片互连电阻、via 良率、CMP 平坦度数据回喂给后道工艺,微调电镀、刻蚀与 CMP 参数,推高互连良率;持续偏移则回看 ⑧ 布线或金属层栈假设。",
  "<b>诚实留痕</b>:本批次 BEOL 的金属层栈、互连电学测试与缺陷数据记入制造工艺档案,作为这颗 die 互连质量可追溯的制造证据,供后续封测/良率分析复查。"
 ],
 "source": "In-Datacenter Performance Analysis of a TPU, Jouppi et al., ISCA 2017(BEOL 多层铜互连、铜双大马士革、low-k ILD、via 层间导通、CMP 平坦化、钝化与焊盘为通行制造实践,非 TPU v1 私有披露)"
}